openai_tiny_function_calling/__init__.py
openai_tiny_function_calling-0.0.1.dist-info/LICENSE
openai_tiny_function_calling-0.0.1.dist-info/METADATA
openai_tiny_function_calling-0.0.1.dist-info/WHEEL
openai_tiny_function_calling-0.0.1.dist-info/top_level.txt
openai_tiny_function_calling-0.0.1.dist-info/RECORD
