Metadata-Version: 2.1
Name: openai-tiny-function-calling
Version: 0.0.1
Author-email: okdshin <kokuzen@gmail.com>
Project-URL: Homepage, https://github.com/okdshin/openai-tiny-function-calling
Project-URL: Bug Tracker, https://github.com/okdshin/openai-tiny-function-calling/issues
Classifier: Programming Language :: Python :: 3
Classifier: License :: OSI Approved :: MIT License
Classifier: Operating System :: OS Independent
Requires-Python: >=3.7
License-File: LICENSE
Provides-Extra: dev
Requires-Dist: build ; extra == 'dev'
Requires-Dist: twine ; extra == 'dev'
